smoosh/__init__.py
smoosh/cli.py
smoosh/custom_types.py
smoosh/pyperclip.pyi
smoosh/version.py
smoosh/analyzer/__init__.py
smoosh/analyzer/repository.py
smoosh/analyzer/tree.py
smoosh/composer/__init__.py
smoosh/composer/concatenator.py
smoosh/composer/formatter.py
smoosh/utils/__init__.py
smoosh/utils/config.py
smoosh/utils/file_utils.py
smoosh/utils/logger.py
smoosh/utils/path_resolver.py
smoosh-0.1.4.dist-info/METADATA
smoosh-0.1.4.dist-info/WHEEL
smoosh-0.1.4.dist-info/entry_points.txt
smoosh-0.1.4.dist-info/licenses/LICENSE
smoosh-0.1.4.dist-info/RECORD
