Metadata-Version: 2.4
Name: smoosh
Version: 0.1.4
Summary: Software Module Outline & Organization Summary Helper
Project-URL: Homepage, https://github.com/j-mcnamara/smoosh
Project-URL: Documentation, https://github.com/j-mcnamara/smoosh#readme
Project-URL: Bug Tracker, https://github.com/j-mcnamara/smoosh/issues
Author: Joshua T. McNamara
License-Expression: MIT
License-File: LICENSE
Keywords: analysis,ast,llm,python,summary
Classifier: Development Status :: 3 - Alpha
Classifier: Intended Audience :: Developers
Classifier: License :: OSI Approved :: MIT License
Classifier: Programming Language :: Python :: 3
Classifier: Programming Language :: Python :: 3.8
Classifier: Programming Language :: Python :: 3.9
Classifier: Programming Language :: Python :: 3.10
Classifier: Programming Language :: Python :: 3.11
Classifier: Topic :: Software Development :: Libraries :: Python Modules
Requires-Python: >=3.9
Requires-Dist: chardet<6.0,>=5.2.0
Requires-Dist: click<9.0,>=8.0
Requires-Dist: pandas>=2.0.0
Requires-Dist: pyperclip<2.0,>=1.8
Requires-Dist: pyyaml<7.0,>=6.0
Requires-Dist: pyyaml>=6.0.0
Requires-Dist: requests>=2.0.0
Requires-Dist: rich<13.0,>=12.0
Requires-Dist: types-pyyaml>=6.0.0
Provides-Extra: dev
Requires-Dist: bandit<2.0.0,>=1.7.8; extra == 'dev'
Requires-Dist: commitizen<4.0.0,>=3.20.0; extra == 'dev'
Requires-Dist: mypy<2.0,>=1.0; extra == 'dev'
Requires-Dist: pre-commit<4.0.0,>=3.5.0; extra == 'dev'
Requires-Dist: pytest-cov<5.0,>=4.0; extra == 'dev'
Requires-Dist: pytest<8.0,>=7.0; extra == 'dev'
Requires-Dist: ruff<0.4.0,>=0.3.0; extra == 'dev'
Requires-Dist: twine<7.0,>=6.0.1; extra == 'dev'
Requires-Dist: types-click>=7.1.8; extra == 'dev'
Requires-Dist: types-pyyaml>=6.0.0; extra == 'dev'
